[
  {
    "title": "Membrana plasmática como barrera selectiva",
    "src": "assets/figures/physio-module2-v227/01_membrana_barrera_selectiva.webp",
    "caption": "Figura 1 — Membrana plasmática como barrera selectiva."
  },
  {
    "title": "Clasificación del transporte de membrana",
    "src": "assets/figures/physio-module2-v227/02_clasificacion_transporte.webp",
    "caption": "Figura 2 — Clasificación del transporte de membrana."
  },
  {
    "title": "Difusión simple vs difusión facilitada",
    "src": "assets/figures/physio-module2-v227/03_difusion_simple_vs_facilitada.webp",
    "caption": "Figura 3 — Difusión simple vs difusión facilitada."
  },
  {
    "title": "Canal vs carrier",
    "src": "assets/figures/physio-module2-v227/04_canal_vs_carrier.webp",
    "caption": "Figura 4 — Canal vs carrier."
  },
  {
    "title": "Bombas ATPasas principales",
    "src": "assets/figures/physio-module2-v227/05_bombas_atpasas.webp",
    "caption": "Figura 5 — Bombas ATPasas principales."
  },
  {
    "title": "Transporte activo primario vs secundario",
    "src": "assets/figures/physio-module2-v227/06_activo_primario_vs_secundario.webp",
    "caption": "Figura 6 — Transporte activo primario vs secundario."
  },
  {
    "title": "Transporte epitelial apical y basolateral",
    "src": "assets/figures/physio-module2-v227/07_epitelial_apical_basolateral.webp",
    "caption": "Figura 7 — Transporte epitelial apical y basolateral."
  },
  {
    "title": "Endocitosis y exocitosis",
    "src": "assets/figures/physio-module2-v227/08_endocitosis_exocitosis.webp",
    "caption": "Figura 8 — Endocitosis y exocitosis."
  }
]